{
  "familyName": "hex_plating",
  "variants": [
    {
      "block": "chisel:hex_plating_0",
      "model_type": "cube_all",
      "name": "hex_plating_0"
    },
    {
      "block": "chisel:hex_plating_1",
      "model_type": "cube_all",
      "name": "hex_plating_1"
    },
    {
      "block": "chisel:hex_plating_2",
      "model_type": "cube_all",
      "name": "hex_plating_2"
    },
    {
      "block": "chisel:hex_plating_3",
      "model_type": "cube_all",
      "name": "hex_plating_3"
    },
    {
      "block": "chisel:hex_plating_4",
      "model_type": "cube_all",
      "name": "hex_plating_4"
    },
    {
      "block": "chisel:hex_plating_5",
      "model_type": "cube_all",
      "name": "hex_plating_5"
    },
    {
      "block": "chisel:hex_plating_6",
      "model_type": "cube_all",
      "name": "hex_plating_6"
    }
  ]
}